{"0": "First Release Feature Specification", "1": "First Release Research", "2": "Child Manager System Architecture", "3": "ADR-0010：受限公网、通行密钥与双条件恢复", "4": "M2 Issue Drafts", "5": "Local Development Environments", "6": "README.md - 产品总纲", "7": "First Release Tasks", "8": "Shell Utility Functions", "9": "Secrets Management Strategy", "10": "Development Rules & Guidelines", "11": "ADR-0003：PostgreSQL 保存任务权威状态，Dramatiq 与 Redis 负责异步执行", "12": "ADR-0005：AI 供应商中立，并建立管理员专用提示词系统", "13": "Child Manager Product and Engineering Roadmap", "14": "Modular Monolith Architecture", "15": "Word Export Templates", "16": "Calendar & Service Degradation", "17": "Word Export Story", "18": "Child Manager Project Constitution", "19": "Teacher Controlled AI Story", "20": "完整 SDD 工作流", "21": "Group Activity Import Story", "22": "M7 Word Export and History", "23": "Q: 请使用/graphify update. 进行更新，同时使用子代理进行语义更新，然后思考还需要完成什么任务", "24": "create-new-feature.sh", "25": "Spec Kit 任务模板", "26": "CONTRIBUTING.md - 贡献指南", "27": "check-prerequisites.sh", "28": "setup-plan.sh", "29": "setup-tasks.sh", "30": "检测与分析报告", "31": "需求与任务语义清单", "32": "Spec Kit 跨制品分析", "33": "澄清焦点与生成清单", "34": "需求写作的单元测试", "35": "Spec Kit 需求检查清单", "36": "歧义与覆盖扫描", "37": "逐问逐答与增量回写", "38": "Spec Kit 规格澄清", "39": "Spec Kit 宪章维护", "40": "宪章同步影响报告", "41": "语义版本与依赖模板同步", "42": "只追加收敛任务", "43": "意图清单与代码差距评估", "44": "Spec Kit 实现收敛", "45": "实施前检查清单门禁", "46": "分阶段任务执行与验证", "47": "阶段一数据模型、契约与验证指南", "48": "阶段零研究与消歧", "49": "规格质量清单迭代验证", "50": "功能目录与可测试规格生成", "51": "依赖、并行与独立验收校验", "52": "按用户故事生成可执行任务", "53": "规范化 Issue 创建", "54": "GitHub 远端匹配与任务去重门禁", "55": "Spec Kit 任务转 GitHub Issue", "56": "检查清单模板", "57": "项目宪章模板", "58": "packages/contracts 共享契约", "59": "提示词管理系统", "60": "避免日期专用文档提交", "61": "Codex 实现子 Issue", "62": "共同基线分支创建", "63": "冲突冻结", "64": "双 Agent 启动前检查清单", "65": "GitHub Issue 创建阶段", "66": "graphify 完整性验收", "67": "graphify 工作区修改处置", "68": "独立授权边界", "69": "实时基线证据", "70": "M1 出口门禁", "71": "M1 Issue 结构", "72": "非破坏性工作区保留", "73": "生产部署非目标", "74": "只读交叉评审", "75": "推荐执行顺序", "76": "共享文档同步", "77": "M1 共享父 Issue", "78": "启动清单循环措辞澄清", "79": "执行停止条件", "80": "T003 共享授权与分支门禁", "81": "T004-T020 实现任务", "82": "TDD 驱动的 M1 实现", "83": "Trae 实现子 Issue", "84": "2026-07-14 只读编码前收敛审查报告", "85": "分支操作授权门禁", "86": "Canonical 阶段状态一致性", "87": "当前不能进入编码", "88": "combined-audit.md", "89": "有条件进入 M1 Issue 设计与草拟阶段", "90": "宪章约束已进入计划与任务", "91": "CONTEXT.md", "92": "双 Agent 开发协议", "93": "Git 与 GitHub 基线", "94": "新报告 Graphify 语义更新待确认", "95": "既有 Graphify 工作区修改", "96": "I-01 Issue 粒度与任务映射", "97": "I-02 启动清单循环措辞", "98": "I-03 工作区基线清洁", "99": "I-04 状态日期", "100": "实现授权门禁", "101": "GitHub Issue 操作授权门禁", "102": "M0-G1 至 M0-G8 已关闭", "103": "M1 Codex 实现子 Issue", "104": "M1 父子 Issue 层级", "105": "M1 共享父 Issue", "106": "M1 Trae 实现子 Issue", "107": "M9 生产部署延后", "108": "plan.md", "109": "双 Agent 只读交叉评审", "110": "docs/ROADMAP.md", "111": "spec.md", "112": "Spec Kit 需求与任务完整覆盖", "113": "T003 双实现分支任务", "114": "T004 至 T020 有序执行清单", "115": "tasks.md", "116": "内容门禁与操作授权分离", "117": "combined-audit 审计事实基线", "118": "最终 docs-only main 共享基线", "119": "Child Manager 20260713 编码前审查报告", "120": "FR-031 快照原因码与恢复顺序", "121": "Git 历史隐私清理", "122": "M0 complete", "123": "M0-G1 至 M0-G8 门禁体系", "124": "M1 ready", "125": "Q13 客户端幂等 scope 与 fingerprint", "126": "T002 Pre-M1 一致性审查", "127": "T003 双 Agent 同基线分支流程", "128": "模板说明契约一致性", "129": "内容门禁与操作授权分离", "130": "模板、FR-031 与 Q13 契约对齐", "131": "M0 阻塞项统一修复执行方案", "132": "历史隐私清理与最终 docs-only 基线", "133": "M0 分阶段修复闭环", "134": "T003 双 Agent 同基线分支流程", "135": "Spec Kit 与 graphify 专项验证门禁", "136": "GitHub Issue 模板配置：禁用空白 Issue", "137": "AI 生成边界", "138": "班级与教师配置", "139": "日期选择与校验", "140": "需要直接比较文件", "141": "AGENTS.md 补充建议查询", "142": "Word 格式边界", "143": "AI 教案结构化", "144": "配置", "145": "区分已确认设计与已实现状态", "146": "日期选择与校验", "147": "CONTEXT.md 补充建议查询", "148": "集成式 NiceGUI 架构", "149": "不继承旧仓库架构", "150": "本地优先架构", "151": "MySQL", "152": "Word 导出格式控制", "153": "一日活动计划 PRD 范围结论", "154": "一日活动计划 PRD 查询记录", "155": "下一份文档查询记录", "156": "系统架构文档作为下一步", "157": "系统架构定义查询记录", "158": "Web API Worker 架构与实施顺序", "159": "旧图谱未覆盖最新架构", "160": "ADR 划分查询记录", "161": "修正后的一日活动计划数据模型结论", "162": "数据模型边界查询记录", "163": "待确认、采用、拒绝与过期", "164": "ai.batch 父任务聚合", "165": "受理、投递、租约与恢复", "166": "执行状态机", "167": "集体活动部分成功", "168": "任务幂等契约", "169": "各任务输入快照", "170": "任务类型", "171": "AI 预览有效性", "172": "模型调用与重试分类", "173": "Web 轮询契约", "174": "表格第二行：星期与日期", "175": "表格第七行：下午户外游戏", "176": "文件第二行：班级与教师", "177": "表格第八行：一日活动反思", "178": "表格第五行：集体活动", "179": "表格第六行：室内区域游戏", "180": "编号、句号、问号与换行格式", "181": "表格第三大行：晨间活动", "182": "表格第四行：晨间谈话", "183": "仅 AI 新增集体环节标红", "184": "一日活动计划 Word 系统说明", "185": "表格第一行：教学周次", "186": "文件第一行：园所与学期月份范围", "187": "右侧列", "188": "右侧列为两行：", "189": "填写说明", "190": "左侧列", "191": "第一行：", "192": "第二行：", "193": "Pyright", "194": "Pytest", "195": "Ruff"}